testAUC/__init__.py
testAUC/evaluate_auc.py
testAUC/temp.py
testAUC/utils.py
testauc-1.1.0.dist-info/licenses/LICENSE
testauc-1.1.0.dist-info/WHEEL
testauc-1.1.0.dist-info/METADATA
testauc-1.1.0.dist-info/RECORD
