Metadata-Version: 2.4
Name: testAUC
Version: 1.1.0
Summary: testAUC is a library of tools to evaluate the true performance of ML/AI models
Author-email: Alonhzn <1833092+alonhzn@users.noreply.github.com>
Requires-Python: >=3.7
Classifier: Programming Language :: Python :: 3
Classifier: License :: OSI Approved :: MIT License
Classifier: Operating System :: OS Independent
License-File: LICENSE
Requires-Dist: scikit-learn
Requires-Dist: matplotlib
Project-URL: Homepage, https://github.com/alonhzn/testAUC
Project-URL: Repository, https://github.com/alonhzn/testAUC
